picoslave/VERSION
picoslave/__init__.py
picoslave/picocli.py
picoslave/picoslave.py
picoslave/version.py
picoslave-1.2.0.data/scripts/picoslave-install
picoslave-1.2.0.dist-info/LICENSE
picoslave-1.2.0.dist-info/METADATA
picoslave-1.2.0.dist-info/WHEEL
picoslave-1.2.0.dist-info/entry_points.txt
picoslave-1.2.0.dist-info/top_level.txt
picoslave-1.2.0.dist-info/RECORD
