Metadata-Version: 2.1
Name: picoslave
Version: 1.2.0
Summary: PicoSlave is a dual I2C slave simulator for hardware integration testing
Home-page: https://gitlab.com/janoskut/picoslave
Author: Janos Kutscherauer
Author-email: janoskut@gmail.com
License: MIT
Keywords: python,Raspberry Pi Pico,I2C,testing,mock
Platform: Linux
Platform: Raspberry Pi
Requires-Python: >=3.7
License-File: LICENSE
Requires-Dist: pyusb (>=1.2)
